{
    "annotations": {
      "list": [
        {
          "builtIn": 1,
          "datasource": "-- Grafana --",
          "enable": true,
          "hide": true,
          "iconColor": "rgba(0, 211, 255, 1)",
          "name": "Annotations & Alerts",
          "type": "dashboard"
        }
      ]
    },
    "editable": true,
    "gnetId": null,
    "graphTooltip": 0,
    "id": 11,
    "iteration": 1563195924077,
    "links": [],
    "panels": [
      {
        "alert": {
          "conditions": [
            {
              "evaluator": {
                "params": [
                  0.5
                ],
                "type": "gt"
              },
              "operator": {
                "type": "and"
              },
              "query": {
                "params": [
                  "A",
                  "5m",
                  "now"
                ]
              },
              "reducer": {
                "params": [],
                "type": "max"
              },
              "type": "query"
            }
          ],
          "executionErrorState": "alerting",
          "for": "5m",
          "frequency": "1m",
          "handler": 1,
          "message": "Warning a node has become unhealthy",
          "name": "Unhealthy Nodes Alert",
          "noDataState": "no_data",
          "notifications": [
            {
              "uid": "aS3KF1IZz"
            },
            {
              "uid": "Ta19APSWz"
            }
          ]
        },
        "aliasColors": {},
        "bars": false,
        "cacheTimeout": null,
        "dashLength": 10,
        "dashes": false,
        "fill": 1,
        "gridPos": {
          "h": 8,
          "w": 6,
          "x": 0,
          "y": 0
        },
        "id": 8,
        "legend": {
          "alignAsTable": false,
          "avg": false,
          "current": false,
          "hideEmpty": true,
          "hideZero": true,
          "max": false,
          "min": false,
          "show": false,
          "total": false,
          "values": false
        },
        "lines": true,
        "linewidth": 1,
        "links": [],
        "nullPointMode": "null",
        "options": {},
        "percentage": false,
        "pluginVersion": "6.2.5",
        "pointradius": 2,
        "points": false,
        "renderer": "flot",
        "seriesOverrides": [],
        "spaceLength": 10,
        "stack": false,
        "steppedLine": false,
        "targets": [
          {
            "expr": "sum(kube_node_status_condition{condition=\"Ready\",status!=\"true\"})",
            "format": "time_series",
            "instant": false,
            "intervalFactor": 1,
            "refId": "A"
          }
        ],
        "thresholds": [
          {
            "colorMode": "critical",
            "fill": true,
            "line": true,
            "op": "gt",
            "value": 0.5
          }
        ],
        "timeFrom": null,
        "timeRegions": [],
        "timeShift": null,
        "title": "Unhealthy Nodes",
        "tooltip": {
          "shared": true,
          "sort": 0,
          "value_type": "individual"
        },
        "type": "graph",
        "xaxis": {
          "buckets": null,
          "mode": "time",
          "name": null,
          "show": true,
          "values": []
        },
        "yaxes": [
          {
            "decimals": 0,
            "format": "short",
            "label": "Unhealthy Nodes",
            "logBase": 1,
            "max": null,
            "min": "0",
            "show": true
          },
          {
            "format": "short",
            "label": null,
            "logBase": 1,
            "max": null,
            "min": null,
            "show": false
          }
        ],
        "yaxis": {
          "align": false,
          "alignLevel": null
        }
      },
      {
        "alert": {
          "conditions": [
            {
              "evaluator": {
                "params": [
                  10
                ],
                "type": "gt"
              },
              "operator": {
                "type": "and"
              },
              "query": {
                "params": [
                  "A",
                  "1m",
                  "now"
                ]
              },
              "reducer": {
                "params": [],
                "type": "max"
              },
              "type": "query"
            }
          ],
          "executionErrorState": "alerting",
          "for": "5m",
          "frequency": "1m",
          "handler": 1,
          "message": "A pod has restarted",
          "name": "Pod Restarts (Cluster) alert",
          "noDataState": "no_data",
          "notifications": [
            {
              "uid": "aS3KF1IZz"
            },
            {
              "uid": "Ta19APSWz"
            }
          ]
        },
        "aliasColors": {},
        "bars": true,
        "dashLength": 10,
        "dashes": false,
        "decimals": 0,
        "fill": 1,
        "gridPos": {
          "h": 8,
          "w": 18,
          "x": 6,
          "y": 0
        },
        "id": 27,
        "legend": {
          "alignAsTable": true,
          "avg": false,
          "current": true,
          "hideEmpty": true,
          "hideZero": true,
          "max": false,
          "min": false,
          "rightSide": true,
          "show": true,
          "total": false,
          "values": true
        },
        "lines": false,
        "linewidth": 1,
        "links": [],
        "nullPointMode": "null as zero",
        "options": {},
        "percentage": false,
        "pointradius": 2,
        "points": false,
        "renderer": "flot",
        "seriesOverrides": [],
        "spaceLength": 10,
        "stack": false,
        "steppedLine": false,
        "targets": [
          {
            "expr": "sum(kube_pod_container_status_restarts_total{container!=\"kube-apiserver\", container!=\"kube-system-fluentd-cloudwatch\", container!=\"etcd-container\", container!=\"weave\"}) by (container, namespace) > 0\n",
            "format": "time_series",
            "instant": false,
            "intervalFactor": 1,
            "refId": "A"
          }
        ],
        "thresholds": [
          {
            "colorMode": "critical",
            "fill": true,
            "line": true,
            "op": "gt",
            "value": 10,
            "yaxis": "left"
          }
        ],
        "timeFrom": null,
        "timeRegions": [],
        "timeShift": null,
        "title": "Pod Restarts (Cluster)",
        "tooltip": {
          "shared": false,
          "sort": 2,
          "value_type": "individual"
        },
        "transparent": true,
        "type": "graph",
        "xaxis": {
          "buckets": null,
          "mode": "series",
          "name": null,
          "show": false,
          "values": [
            "current"
          ]
        },
        "yaxes": [
          {
            "decimals": 0,
            "format": "short",
            "label": null,
            "logBase": 1,
            "max": null,
            "min": null,
            "show": true
          },
          {
            "format": "short",
            "label": null,
            "logBase": 1,
            "max": null,
            "min": null,
            "show": true
          }
        ],
        "yaxis": {
          "align": false,
          "alignLevel": null
        }
      },
      {
        "alert": {
          "conditions": [
            {
              "evaluator": {
                "params": [
                  80
                ],
                "type": "gt"
              },
              "operator": {
                "type": "and"
              },
              "query": {
                "params": [
                  "A",
                  "5m",
                  "now"
                ]
              },
              "reducer": {
                "params": [],
                "type": "avg"
              },
              "type": "query"
            }
          ],
          "executionErrorState": "alerting",
          "for": "5m",
          "frequency": "1m",
          "handler": 1,
          "message": "Node CPU Usage has spiked",
          "name": "Node CPU Usage alert",
          "noDataState": "no_data",
          "notifications": [
            {
              "uid": "aS3KF1IZz"
            },
            {
              "uid": "Ta19APSWz"
            }
          ]
        },
        "aliasColors": {},
        "bars": false,
        "dashLength": 10,
        "dashes": false,
        "fill": 1,
        "gridPos": {
          "h": 8,
          "w": 24,
          "x": 0,
          "y": 8
        },
        "id": 25,
        "legend": {
          "avg": false,
          "current": false,
          "max": false,
          "min": false,
          "show": true,
          "total": false,
          "values": false
        },
        "lines": true,
        "linewidth": 1,
        "links": [],
        "nullPointMode": "null",
        "options": {},
        "percentage": false,
        "pointradius": 2,
        "points": false,
        "renderer": "flot",
        "seriesOverrides": [],
        "spaceLength": 10,
        "stack": false,
        "steppedLine": false,
        "targets": [
          {
            "expr": "100 - (avg by (instance) (irate(node_cpu_seconds_total{mode=\"idle\"}[5m])) * 100)",
            "format": "time_series",
            "intervalFactor": 1,
            "refId": "A"
          }
        ],
        "thresholds": [
          {
            "colorMode": "critical",
            "fill": true,
            "line": true,
            "op": "gt",
            "value": 80
          }
        ],
        "timeFrom": null,
        "timeRegions": [],
        "timeShift": null,
        "title": "Node CPU Usage",
        "tooltip": {
          "shared": false,
          "sort": 2,
          "value_type": "individual"
        },
        "transparent": true,
        "type": "graph",
        "xaxis": {
          "buckets": null,
          "mode": "time",
          "name": null,
          "show": true,
          "values": []
        },
        "yaxes": [
          {
            "format": "short",
            "label": null,
            "logBase": 1,
            "max": "100",
            "min": "0",
            "show": true
          },
          {
            "format": "short",
            "label": null,
            "logBase": 1,
            "max": null,
            "min": null,
            "show": true
          }
        ],
        "yaxis": {
          "align": false,
          "alignLevel": null
        }
      },
      {
        "alert": {
          "conditions": [
            {
              "evaluator": {
                "params": [
                  85
                ],
                "type": "gt"
              },
              "operator": {
                "type": "and"
              },
              "query": {
                "params": [
                  "A",
                  "5m",
                  "now"
                ]
              },
              "reducer": {
                "params": [],
                "type": "avg"
              },
              "type": "query"
            }
          ],
          "executionErrorState": "alerting",
          "for": "5m",
          "frequency": "1m",
          "handler": 1,
          "message": "Node Memory Usage has spiked",
          "name": "Nodes Memory Usage alert",
          "noDataState": "no_data",
          "notifications": [
            {
              "uid": "aS3KF1IZz"
            },
            {
              "uid": "Ta19APSWz"
            }
          ]
        },
        "aliasColors": {},
        "bars": false,
        "cacheTimeout": null,
        "dashLength": 10,
        "dashes": false,
        "decimals": 0,
        "fill": 0,
        "gridPos": {
          "h": 8,
          "w": 24,
          "x": 0,
          "y": 16
        },
        "id": 23,
        "legend": {
          "alignAsTable": false,
          "avg": false,
          "current": true,
          "hideEmpty": false,
          "hideZero": false,
          "max": false,
          "min": false,
          "rightSide": false,
          "show": true,
          "total": false,
          "values": true
        },
        "lines": true,
        "linewidth": 1,
        "links": [],
        "nullPointMode": "null",
        "options": {},
        "percentage": false,
        "pluginVersion": "6.1.6",
        "pointradius": 2,
        "points": false,
        "renderer": "flot",
        "seriesOverrides": [],
        "spaceLength": 10,
        "stack": false,
        "steppedLine": false,
        "targets": [
          {
            "expr": "((1 - ((node_memory_MemFree_bytes + node_memory_Cached_bytes) / node_memory_MemTotal_bytes)) * 100)",
            "format": "time_series",
            "intervalFactor": 1,
            "refId": "A"
          }
        ],
        "thresholds": [
          {
            "colorMode": "critical",
            "fill": true,
            "line": true,
            "op": "gt",
            "value": 85
          }
        ],
        "timeFrom": null,
        "timeRegions": [],
        "timeShift": null,
        "title": "Nodes Memory Usage",
        "tooltip": {
          "shared": true,
          "sort": 2,
          "value_type": "individual"
        },
        "transparent": true,
        "type": "graph",
        "xaxis": {
          "buckets": null,
          "mode": "time",
          "name": null,
          "show": true,
          "values": []
        },
        "yaxes": [
          {
            "decimals": 0,
            "format": "short",
            "label": null,
            "logBase": 1,
            "max": "100",
            "min": "0",
            "show": true
          },
          {
            "format": "short",
            "label": null,
            "logBase": 1,
            "max": null,
            "min": null,
            "show": false
          }
        ],
        "yaxis": {
          "align": false,
          "alignLevel": null
        }
      },
      {
        "content": "---\n# RabbitMQ\n---",
        "description": "",
        "gridPos": {
          "h": 3,
          "w": 24,
          "x": 0,
          "y": 24
        },
        "id": 37,
        "links": [],
        "mode": "markdown",
        "options": {},
        "targets": [
          {
            "expr": "",
            "format": "time_series",
            "intervalFactor": 1,
            "refId": "A"
          }
        ],
        "timeFrom": null,
        "timeShift": null,
        "title": "",
        "transparent": true,
        "type": "text"
      },
      {
        "alert": {
          "conditions": [
            {
              "evaluator": {
                "params": [
                  400
                ],
                "type": "gt"
              },
              "operator": {
                "type": "and"
              },
              "query": {
                "params": [
                  "A",
                  "5m",
                  "now"
                ]
              },
              "reducer": {
                "params": [],
                "type": "avg"
              },
              "type": "query"
            }
          ],
          "executionErrorState": "alerting",
          "for": "5m",
          "frequency": "1m",
          "handler": 1,
          "message": "RabbitMQ Connections have spiked",
          "name": "RabbitMQ Channels alert",
          "noDataState": "no_data",
          "notifications": [
            {
              "uid": "aS3KF1IZz"
            },
            {
              "uid": "Ta19APSWz"
            }
          ]
        },
        "aliasColors": {},
        "bars": false,
        "dashLength": 10,
        "dashes": false,
        "decimals": 0,
        "fill": 1,
        "gridPos": {
          "h": 8,
          "w": 12,
          "x": 0,
          "y": 27
        },
        "id": 29,
        "legend": {
          "alignAsTable": true,
          "avg": false,
          "current": true,
          "max": false,
          "min": false,
          "rightSide": true,
          "show": true,
          "total": false,
          "values": true
        },
        "lines": true,
        "linewidth": 1,
        "links": [],
        "nullPointMode": "null",
        "options": {},
        "percentage": false,
        "pointradius": 2,
        "points": false,
        "renderer": "flot",
        "seriesOverrides": [],
        "spaceLength": 10,
        "stack": false,
        "steppedLine": false,
        "targets": [
          {
            "expr": "sum(rabbitmq_channelsTotal) by (instance, kubernetes_namespace)",
            "format": "time_series",
            "intervalFactor": 1,
            "refId": "A"
          }
        ],
        "thresholds": [
          {
            "colorMode": "critical",
            "fill": true,
            "line": true,
            "op": "gt",
            "value": 400
          }
        ],
        "timeFrom": null,
        "timeRegions": [],
        "timeShift": null,
        "title": "RabbitMQ Channels",
        "tooltip": {
          "shared": true,
          "sort": 0,
          "value_type": "individual"
        },
        "transparent": true,
        "type": "graph",
        "xaxis": {
          "buckets": null,
          "mode": "time",
          "name": null,
          "show": true,
          "values": []
        },
        "yaxes": [
          {
            "format": "short",
            "label": "RabbitMQ Channels",
            "logBase": 1,
            "max": null,
            "min": null,
            "show": true
          },
          {
            "format": "short",
            "label": null,
            "logBase": 1,
            "max": null,
            "min": null,
            "show": true
          }
        ],
        "yaxis": {
          "align": false,
          "alignLevel": null
        }
      },
      {
        "alert": {
          "conditions": [
            {
              "evaluator": {
                "params": [
                  150
                ],
                "type": "gt"
              },
              "operator": {
                "type": "and"
              },
              "query": {
                "params": [
                  "A",
                  "5m",
                  "now"
                ]
              },
              "reducer": {
                "params": [],
                "type": "avg"
              },
              "type": "query"
            }
          ],
          "executionErrorState": "alerting",
          "for": "5m",
          "frequency": "1m",
          "handler": 1,
          "message": "Rabbit Connections have spiked",
          "name": "Rabbit Connections Alert",
          "noDataState": "no_data",
          "notifications": [
            {
              "uid": "aS3KF1IZz"
            },
            {
              "uid": "Ta19APSWz"
            }
          ]
        },
        "aliasColors": {},
        "bars": false,
        "dashLength": 10,
        "dashes": false,
        "decimals": 0,
        "fill": 1,
        "gridPos": {
          "h": 8,
          "w": 12,
          "x": 12,
          "y": 27
        },
        "id": 31,
        "legend": {
          "alignAsTable": true,
          "avg": false,
          "current": true,
          "max": false,
          "min": false,
          "rightSide": true,
          "show": true,
          "total": false,
          "values": true
        },
        "lines": true,
        "linewidth": 1,
        "links": [],
        "nullPointMode": "null",
        "options": {},
        "percentage": false,
        "pointradius": 2,
        "points": false,
        "renderer": "flot",
        "seriesOverrides": [],
        "spaceLength": 10,
        "stack": false,
        "steppedLine": false,
        "targets": [
          {
            "expr": "sum(rabbitmq_connectionsTotal) by (instance, kubernetes_namespace)\n",
            "format": "time_series",
            "intervalFactor": 1,
            "refId": "A"
          }
        ],
        "thresholds": [
          {
            "colorMode": "critical",
            "fill": true,
            "line": true,
            "op": "gt",
            "value": 150
          }
        ],
        "timeFrom": null,
        "timeRegions": [],
        "timeShift": null,
        "title": "Rabbit Connections",
        "tooltip": {
          "shared": true,
          "sort": 0,
          "value_type": "individual"
        },
        "transparent": true,
        "type": "graph",
        "xaxis": {
          "buckets": null,
          "mode": "time",
          "name": null,
          "show": true,
          "values": []
        },
        "yaxes": [
          {
            "format": "short",
            "label": "Rabbit Connections",
            "logBase": 1,
            "max": null,
            "min": null,
            "show": true
          },
          {
            "format": "short",
            "label": null,
            "logBase": 1,
            "max": null,
            "min": null,
            "show": true
          }
        ],
        "yaxis": {
          "align": false,
          "alignLevel": null
        }
      },
      {
        "alert": {
          "conditions": [
            {
              "evaluator": {
                "params": [
                  350
                ],
                "type": "gt"
              },
              "operator": {
                "type": "and"
              },
              "query": {
                "params": [
                  "A",
                  "5m",
                  "now"
                ]
              },
              "reducer": {
                "params": [],
                "type": "avg"
              },
              "type": "query"
            }
          ],
          "executionErrorState": "alerting",
          "for": "5m",
          "frequency": "1m",
          "handler": 1,
          "message": "RabbitMQ Consumers have spiked",
          "name": "RabbitMQ Consumers alert",
          "noDataState": "no_data",
          "notifications": [
            {
              "uid": "aS3KF1IZz"
            },
            {
              "uid": "Ta19APSWz"
            }
          ]
        },
        "aliasColors": {},
        "bars": false,
        "dashLength": 10,
        "dashes": false,
        "decimals": 0,
        "fill": 1,
        "gridPos": {
          "h": 8,
          "w": 12,
          "x": 0,
          "y": 35
        },
        "id": 33,
        "interval": "",
        "legend": {
          "alignAsTable": true,
          "avg": false,
          "current": true,
          "max": false,
          "min": false,
          "rightSide": true,
          "show": true,
          "total": false,
          "values": true
        },
        "lines": true,
        "linewidth": 1,
        "links": [],
        "nullPointMode": "null",
        "options": {},
        "percentage": false,
        "pointradius": 2,
        "points": false,
        "renderer": "flot",
        "seriesOverrides": [],
        "spaceLength": 10,
        "stack": false,
        "steppedLine": false,
        "targets": [
          {
            "expr": "sum(rabbitmq_consumersTotal) by (instance, kubernetes_namespace)",
            "format": "time_series",
            "intervalFactor": 1,
            "refId": "A"
          }
        ],
        "thresholds": [
          {
            "colorMode": "critical",
            "fill": true,
            "line": true,
            "op": "gt",
            "value": 350
          }
        ],
        "timeFrom": null,
        "timeRegions": [],
        "timeShift": null,
        "title": "RabbitMQ Consumers",
        "tooltip": {
          "shared": true,
          "sort": 0,
          "value_type": "individual"
        },
        "transparent": true,
        "type": "graph",
        "xaxis": {
          "buckets": null,
          "mode": "time",
          "name": null,
          "show": true,
          "values": []
        },
        "yaxes": [
          {
            "format": "short",
            "label": "RabbitMQ Consumers",
            "logBase": 1,
            "max": null,
            "min": null,
            "show": true
          },
          {
            "format": "short",
            "label": null,
            "logBase": 1,
            "max": null,
            "min": null,
            "show": true
          }
        ],
        "yaxis": {
          "align": false,
          "alignLevel": null
        }
      },
      {
        "alert": {
          "conditions": [
            {
              "evaluator": {
                "params": [
                  20
                ],
                "type": "gt"
              },
              "operator": {
                "type": "and"
              },
              "query": {
                "params": [
                  "A",
                  "5m",
                  "now"
                ]
              },
              "reducer": {
                "params": [],
                "type": "avg"
              },
              "type": "query"
            }
          ],
          "executionErrorState": "alerting",
          "for": "5m",
          "frequency": "1m",
          "handler": 1,
          "message": "RabbitMQ Exchanges have spiked",
          "name": "RabbitMQ Exchanges alert",
          "noDataState": "no_data",
          "notifications": [
            {
              "uid": "aS3KF1IZz"
            },
            {
              "uid": "Ta19APSWz"
            }
          ]
        },
        "aliasColors": {},
        "bars": false,
        "dashLength": 10,
        "dashes": false,
        "decimals": 0,
        "fill": 1,
        "gridPos": {
          "h": 8,
          "w": 12,
          "x": 12,
          "y": 35
        },
        "id": 35,
        "legend": {
          "alignAsTable": true,
          "avg": false,
          "current": true,
          "hideEmpty": false,
          "hideZero": false,
          "max": false,
          "min": false,
          "rightSide": true,
          "show": true,
          "total": false,
          "values": true
        },
        "lines": true,
        "linewidth": 1,
        "links": [],
        "nullPointMode": "null",
        "options": {},
        "percentage": false,
        "pointradius": 2,
        "points": false,
        "renderer": "flot",
        "seriesOverrides": [],
        "spaceLength": 10,
        "stack": false,
        "steppedLine": false,
        "targets": [
          {
            "expr": "sum(rabbitmq_exchangesTotal) by (instance, kubernetes_namespace)",
            "format": "time_series",
            "instant": false,
            "intervalFactor": 1,
            "refId": "A"
          }
        ],
        "thresholds": [
          {
            "colorMode": "critical",
            "fill": true,
            "line": true,
            "op": "gt",
            "value": 20
          }
        ],
        "timeFrom": null,
        "timeRegions": [],
        "timeShift": null,
        "title": "RabbitMQ Exchanges",
        "tooltip": {
          "shared": true,
          "sort": 0,
          "value_type": "individual"
        },
        "type": "graph",
        "xaxis": {
          "buckets": null,
          "mode": "time",
          "name": null,
          "show": true,
          "values": []
        },
        "yaxes": [
          {
            "format": "short",
            "label": "RabbitMQ Exchanges",
            "logBase": 1,
            "max": null,
            "min": null,
            "show": true
          },
          {
            "format": "short",
            "label": null,
            "logBase": 1,
            "max": null,
            "min": null,
            "show": true
          }
        ],
        "yaxis": {
          "align": false,
          "alignLevel": null
        }
      }
    ],
    "refresh": false,
    "schemaVersion": 18,
    "style": "dark",
    "tags": [],
    "templating": {
      "list": [
        {
          "datasource": null,
          "filters": [],
          "hide": 0,
          "label": "",
          "name": "Filters",
          "skipUrlSync": false,
          "type": "adhoc"
        }
      ]
    },
    "time": {
      "from": "now-6h",
      "to": "now"
    },
    "timepicker": {
      "refresh_intervals": [
        "5s",
        "10s",
        "30s",
        "1m",
        "5m",
        "15m",
        "30m",
        "1h",
        "2h",
        "1d"
      ],
      "time_options": [
        "5m",
        "15m",
        "1h",
        "6h",
        "12h",
        "24h",
        "2d",
        "7d",
        "30d"
      ]
    },
    "timezone": "",
    "title": "Harmony Alerts",
    "version": 7
  }